square_administration/__init__.py
square_administration/configuration.py
square_administration/data/config.sample.ini
square_administration/data/config.testing.sample.ini
square_administration/main.py
square_administration/messages.py
square_administration/pydantic_models/__init__.py
square_administration/pydantic_models/authentication.py
square_administration/pydantic_models/core.py
square_administration/routes/__init__.py
square_administration/routes/authentication.py
square_administration/routes/core.py
square_administration/utils/__init__.py
square_administration/utils/common.py
square_administration/utils/routes/__init__.py
square_administration/utils/routes/authentication.py
square_administration/utils/routes/core.py
square_administration-4.0.1.dist-info/WHEEL
square_administration-4.0.1.dist-info/METADATA
square_administration-4.0.1.dist-info/RECORD
