Metadata-Version: 2.3
Name: square_administration
Version: 4.0.1
Summary: common business layer for my personal server.
Keywords: administration,fastapi,backend
Author: Parth Mukesh Mangtani
Author-email: Parth Mukesh Mangtani <thepmsquare@gmail.com>
License: GPLv3
Classifier: Development Status :: 3 - Alpha
Classifier: Intended Audience :: Developers
Classifier: License :: OSI Approved :: GNU General Public License v3 (GPLv3)
Classifier: Programming Language :: Python :: 3
Classifier: Programming Language :: Python :: 3.12
Classifier: Programming Language :: Python :: 3 :: Only
Classifier: Topic :: Utilities
Classifier: Topic :: Internet :: WWW/HTTP :: Dynamic Content
Classifier: Framework :: FastAPI
Requires-Dist: uvicorn>=0.24.0.post1
Requires-Dist: fastapi>=0.104.1
Requires-Dist: pydantic>=2.5.3
Requires-Dist: requests>=2.32.3
Requires-Dist: bcrypt>=4.2.0
Requires-Dist: httpx>=0.27.2
Requires-Dist: square-commons>=2.1.0
Requires-Dist: square-logger>=3.0.0
Requires-Dist: square-database-helper>=2.7.1
Requires-Dist: square-database-structure>=1.0.0
Requires-Dist: square-authentication-helper>=3.0.0
Requires-Dist: pytest>=8.3.3 ; extra == 'all'
Requires-Dist: pytest>=8.3.3 ; extra == 'dev'
Requires-Python: >=3.12
Project-URL: homepage, https://github.com/thepmsquare/square_administration
Provides-Extra: all
Provides-Extra: dev
